setup.py
alibabacloud_gateway_oss/__init__.py
alibabacloud_gateway_oss/client.py
alibabacloud_gateway_oss_py2.egg-info/PKG-INFO
alibabacloud_gateway_oss_py2.egg-info/SOURCES.txt
alibabacloud_gateway_oss_py2.egg-info/dependency_links.txt
alibabacloud_gateway_oss_py2.egg-info/requires.txt
alibabacloud_gateway_oss_py2.egg-info/top_level.txt